LICENSE
MANIFEST.in
README.md
libalgebra.h
libflagstats.c
libflagstats.h
libflagstats.pyx
setup.cfg
setup.py
pyflagstats.egg-info/PKG-INFO
pyflagstats.egg-info/SOURCES.txt
pyflagstats.egg-info/dependency_links.txt
pyflagstats.egg-info/requires.txt
pyflagstats.egg-info/top_level.txt