Metadata-Version: 2.1
Name: pyflagstats
Version: 0.1.4
Summary: Efficient subroutines for computing summary statistics for the SAM FLAG field
Home-page: https://github.com/mklarqvist/libflagstats
Author: Marcus D. R. Klarqvist
Author-email: mk819@cam.ac.uk
License: Apache 2.0
Keywords: simd,popcount,popcnt,pospopcnt,hts,ngs,flags
Platform: Linux
Platform: MacOSX
Platform: Windows
Classifier: Development Status :: 4 - Beta
Classifier: Topic :: Scientific/Engineering :: Bio-Informatics
Classifier: Intended Audience :: Science/Research
Classifier: Programming Language :: Python :: 3
